CHANGES.txt
README.txt
bootstrap.py
buildout.cfg
setup.py
src/z3c/__init__.py
src/z3c.testsummarizer.egg-info/PKG-INFO
src/z3c.testsummarizer.egg-info/SOURCES.txt
src/z3c.testsummarizer.egg-info/dependency_links.txt
src/z3c.testsummarizer.egg-info/entry_points.txt
src/z3c.testsummarizer.egg-info/namespace_packages.txt
src/z3c.testsummarizer.egg-info/not-zip-safe
src/z3c.testsummarizer.egg-info/requires.txt
src/z3c.testsummarizer.egg-info/top_level.txt
src/z3c/testsummarizer/__init__.py
src/z3c/testsummarizer/archive.py
src/z3c/testsummarizer/format.py
src/z3c/testsummarizer/main.py
src/z3c/testsummarizer/message.py
src/z3c/testsummarizer/tests/__init__.py
src/z3c/testsummarizer/tests/fixtures/2011-February/030644.html
src/z3c/testsummarizer/tests/fixtures/2011-February/030645.html
src/z3c/testsummarizer/tests/fixtures/2011-February/030646.html
src/z3c/testsummarizer/tests/fixtures/2011-February/030647.html
src/z3c/testsummarizer/tests/fixtures/2011-February/030648.html
src/z3c/testsummarizer/tests/fixtures/2011-February/030649.html
src/z3c/testsummarizer/tests/fixtures/2011-February/030650.html
src/z3c/testsummarizer/tests/fixtures/2011-February/030651.html
src/z3c/testsummarizer/tests/fixtures/2011-February/030652.html
src/z3c/testsummarizer/tests/fixtures/2011-February/030653.html
src/z3c/testsummarizer/tests/fixtures/2011-February/030654.html
src/z3c/testsummarizer/tests/fixtures/2011-February/030655.html
src/z3c/testsummarizer/tests/fixtures/2011-February/030656.html
src/z3c/testsummarizer/tests/fixtures/2011-February/030657.html
src/z3c/testsummarizer/tests/fixtures/2011-February/030658.html
src/z3c/testsummarizer/tests/fixtures/2011-February/030659.html
src/z3c/testsummarizer/tests/fixtures/2011-February/030660.html
src/z3c/testsummarizer/tests/fixtures/2011-February/030661.html
src/z3c/testsummarizer/tests/fixtures/2011-February/030662.html
src/z3c/testsummarizer/tests/fixtures/2011-February/030663.html
src/z3c/testsummarizer/tests/fixtures/2011-February/030664.html
src/z3c/testsummarizer/tests/fixtures/2011-February/030665.html
src/z3c/testsummarizer/tests/fixtures/2011-February/030666.html
src/z3c/testsummarizer/tests/fixtures/2011-February/030667.html
src/z3c/testsummarizer/tests/fixtures/2011-February/030668.html
src/z3c/testsummarizer/tests/fixtures/2011-February/030669.html
