Metadata-Version: 1.0
Name: z3c.testsummarizer
Version: 2.0
Summary: UNKNOWN
Home-page: UNKNOWN
Author: Stefan Holek, Christian Theune, Wolfgang Schnerring
Author-email: ws@gocept.com
License: ZPL 2.1
Platform: UNKNOWN
